librarypp/__init__.py
librarypp/main.py
bot_pp-0.1.dist-info/METADATA
bot_pp-0.1.dist-info/WHEEL
bot_pp-0.1.dist-info/entry_points.txt
bot_pp-0.1.dist-info/top_level.txt
bot_pp-0.1.dist-info/RECORD
