Metadata-Version: 2.1
Name: bot-pp
Version: 0.1
Summary: A library that creates a Python bot
Home-page: https://ppbot.web.app/mylibrary
Author: P
Author-email: parepare2154@gmail.com
Classifier: Programming Language :: Python :: 3
Classifier: License :: OSI Approved :: MIT License
Classifier: Operating System :: OS Independent
